mdreg/__init__.py
mdreg/ants.py
mdreg/data.py
mdreg/elastix.py
mdreg/fit_models.py
mdreg/io.py
mdreg/main.py
mdreg/pixel_models.py
mdreg/plot.py
mdreg/skimage.py
mdreg/utils.py
mdreg/datafiles/VFA.pkl
mdreg/datafiles/__init__.py
mdreg-0.5.3.dist-info/licenses/LICENSE
mdreg-0.5.3.dist-info/METADATA
mdreg-0.5.3.dist-info/WHEEL
mdreg-0.5.3.dist-info/top_level.txt
mdreg-0.5.3.dist-info/RECORD
