Metadata-Version: 2.4
Name: mdreg
Version: 0.5.3
Summary: Model-driven image registration
Author-email: Steven Sourbron <s.sourbron@sheffield.ac.uk>
License: Apache License
Project-URL: Homepage, https://openmiblab.github.io/mdreg
Project-URL: Source Code, https://github.com/openmiblab/mdreg
Keywords: python,medical imaging,motion correction,registration
Classifier: Development Status :: 3 - Alpha
Classifier: Intended Audience :: Developers
Classifier: Intended Audience :: Science/Research
Classifier: Topic :: Scientific/Engineering
Classifier: Environment :: Console
Classifier: Operating System :: OS Independent
Classifier: License :: OSI Approved :: Apache Software License
Classifier: Programming Language :: Python
Classifier: Programming Language :: Python :: 3
Requires-Python: >=3.6
License-File: LICENSE
Requires-Dist: importlib-resources>=1.1.0
Requires-Dist: tqdm
Requires-Dist: numpy
Requires-Dist: scipy
Requires-Dist: scikit-image
Requires-Dist: zarr
Requires-Dist: dask
Requires-Dist: requests
Provides-Extra: complete
Requires-Dist: antspyx; extra == "complete"
Requires-Dist: itk-elastix; extra == "complete"
Requires-Dist: matplotlib; extra == "complete"
Requires-Dist: Pillow; extra == "complete"
Provides-Extra: elastix
Requires-Dist: itk-elastix; extra == "elastix"
Provides-Extra: ants
Requires-Dist: antspyx; extra == "ants"
Provides-Extra: plot
Requires-Dist: matplotlib; extra == "plot"
Requires-Dist: Pillow; extra == "plot"
Dynamic: license-file
